STASCAN/StatPlot.py
STASCAN/__init__.py
STASCAN/downstream.py
STASCAN/model.py
STASCAN/preparation.py
STASCAN/preparation_dbit.py
STASCAN/run_STASCAN.py
STASCAN/run_STASCAN_dbit.py
STASCAN-1.1.0.dist-info/LICENSE.txt
STASCAN-1.1.0.dist-info/METADATA
STASCAN-1.1.0.dist-info/WHEEL
STASCAN-1.1.0.dist-info/top_level.txt
STASCAN-1.1.0.dist-info/RECORD
