Metadata-Version: 2.1
Name: STASCAN
Version: 1.1.0
Summary: An AI-driven method for enhanced cellular organizational map in spatial transcriptomics
Home-page: https://github.com/AbbyWY/STASCAN
Author: Ying Wu
Author-email: wuy@big.ac.cn
License: MIT
Platform: UNKNOWN
Requires-Dist: requests
